salted/__init__.py
salted/__main__.py
salted/cache_reader.py
salted/command_line.py
salted/database_io.py
salted/doi_check.py
salted/err.py
salted/file_finder.py
salted/input_handler.py
salted/memory_instance.py
salted/parser.py
salted/py.typed
salted/rate_limiter.py
salted/report_generator.py
salted/templates/default.cli.jinja
salted/templates/default.md.jinja
salted/url_check.py
salted/user_agents.py
salted-1.0.1.dist-info/METADATA
salted-1.0.1.dist-info/WHEEL
salted-1.0.1.dist-info/entry_points.txt
salted-1.0.1.dist-info/licenses/LICENSE
salted-1.0.1.dist-info/RECORD
