Metadata-Version: 2.4
Name: salted
Version: 1.0.1
Summary: Smart, Asynchronous Link Tester with Database backend
License: Apache-2.0
License-File: LICENSE
Keywords: link-checker,url-validation,html,markdown,latex,bibtex,async
Author: Rüdiger Voigt
Author-email: projects@ruediger-voigt.eu
Requires-Python: >=3.10,<4.0
Classifier: Development Status :: 5 - Production/Stable
Classifier: Framework :: AsyncIO
Classifier: Intended Audience :: Developers
Classifier: Intended Audience :: System Administrators
Classifier: License :: OSI Approved :: Apache Software License
Classifier: Operating System :: OS Independent
Classifier: Programming Language :: Python :: 3
Classifier: Programming Language :: Python :: 3.10
Classifier: Programming Language :: Python :: 3.11
Classifier: Programming Language :: Python :: 3.12
Classifier: Programming Language :: Python :: 3.13
Classifier: Programming Language :: Python :: 3.14
Classifier: Topic :: Internet :: WWW/HTTP :: Indexing/Search
Classifier: Topic :: Internet :: WWW/HTTP :: Site Management
Classifier: Topic :: Internet :: WWW/HTTP :: Site Management :: Link Checking
Classifier: Topic :: Text Processing :: Markup :: HTML
Requires-Dist: aiodns (>=3.5.0)
Requires-Dist: aiohttp (>=3.13.2)
Requires-Dist: beautifulsoup4 (>=4.14.2)
Requires-Dist: compatibility (>=2.0.0)
Requires-Dist: jinja2 (>=3.1.5)
Requires-Dist: lxml (>=6.0.2)
Requires-Dist: pybtex (>=0.25.1)
Requires-Dist: tqdm (>=4.67.1)
Requires-Dist: userprovided (>=2.1.1)
Project-URL: Bug Tracker, https://github.com/RuedigerVoigt/salted/issues
Project-URL: Changelog, https://github.com/RuedigerVoigt/salted/blob/main/CHANGELOG.md
Project-URL: Homepage, https://github.com/RuedigerVoigt/salted
Project-URL: Repository, https://github.com/RuedigerVoigt/salted
